setup.py
ts_chinese_poem_generator/__init__.py
ts_chinese_poem_generator/generator.py
ts_chinese_poem_generator/title_rhythm.py
ts_chinese_poem_generator.egg-info/PKG-INFO
ts_chinese_poem_generator.egg-info/SOURCES.txt
ts_chinese_poem_generator.egg-info/dependency_links.txt
ts_chinese_poem_generator.egg-info/not-zip-safe
ts_chinese_poem_generator.egg-info/requires.txt
ts_chinese_poem_generator.egg-info/top_level.txt