Metadata-Version: 1.0
Name: ts-chinese-poem-generator
Version: 0.2
Summary: Chinese Poem Generator
Home-page: https://github.com/linpingta/chinese-poem-generator.git
Author: ChuTong
Author-email: linpingta@163.com
License: MIT
Keywords: chinese,poem
Platform: UNKNOWN
